{
  "schema_version": "3.2.1",
  "last_migration": "20260111000003_email_notifications.sql",
  "total_migrations": 65,
  "migrations": [
    {"filename": "20250101000000_initial_schema.sql", "timestamp": "2025-01-01T00:00:00Z", "phase": "Phase 1: Foundation", "description": "initial schema"},
    {"filename": "20250109_media_system.sql", "timestamp": "2025-01-09T_m:ed:iaZ", "phase": "Phase 1: Foundation", "description": "media system"},
    {"filename": "20250913000000_rbac_enum_types.sql", "timestamp": "2025-09-13T00:00:00Z", "phase": "Phase 1: Foundation", "description": "rbac enum types"},
    {"filename": "20250913005713_create_organization_roles_table.sql", "timestamp": "2025-09-13T00:57:13Z", "phase": "Phase 1: Foundation", "description": "create organization roles table"},
    {"filename": "20250913_enhance_organizations_cultural_identity.sql", "timestamp": "2025-09-13T_e:nh:anZ", "phase": "Phase 1: Foundation", "description": "enhance organizations cultural identity"},
    {"filename": "20250916_storyteller_analytics_foundation.sql", "timestamp": "2025-09-16T_s:to:ryZ", "phase": "Phase 1: Foundation", "description": "storyteller analytics foundation"},
    {"filename": "20250916_storyteller_dashboard_analytics.sql", "timestamp": "2025-09-16T_s:to:ryZ", "phase": "Phase 1: Foundation", "description": "storyteller dashboard analytics"},
    {"filename": "20250916_storyteller_network_discovery.sql", "timestamp": "2025-09-16T_s:to:ryZ", "phase": "Phase 1: Foundation", "description": "storyteller network discovery"},
    {"filename": "20250917_enhance_storyteller_profiles.sql", "timestamp": "2025-09-17T_e:nh:anZ", "phase": "Phase 1: Foundation", "description": "enhance storyteller profiles"},
    {"filename": "20251004_fix_missing_fields.sql", "timestamp": "2025-10-04T_f:ix:_mZ", "phase": "Phase 1: Foundation", "description": "fix missing fields"},
    {"filename": "20251005_force_postgrest_refresh.sql", "timestamp": "2025-10-05T_f:or:ceZ", "phase": "Phase 1: Foundation", "description": "force postgrest refresh"},
    {"filename": "20251005_storyteller_schema_enhancement.sql", "timestamp": "2025-10-05T_s:to:ryZ", "phase": "Phase 1: Foundation", "description": "storyteller schema enhancement"},
    {"filename": "20251010_project_analysis_cache.sql", "timestamp": "2025-10-10T_p:ro:jeZ", "phase": "Phase 1: Foundation", "description": "project analysis cache"},
    {"filename": "20251010_project_analysis_cache_v2.sql", "timestamp": "2025-10-10T_p:ro:jeZ", "phase": "Phase 1: Foundation", "description": "project analysis cache v2"},
    {"filename": "20251011_organization_contexts.sql", "timestamp": "2025-10-11T_o:rg:anZ", "phase": "Phase 1: Foundation", "description": "organization contexts"},
    {"filename": "20251011_project_context.sql", "timestamp": "2025-10-11T_p:ro:jeZ", "phase": "Phase 1: Foundation", "description": "project context"},
    {"filename": "20251011_project_contexts.sql", "timestamp": "2025-10-11T_p:ro:jeZ", "phase": "Phase 1: Foundation", "description": "project contexts"},
    {"filename": "20251011_seed_interview_templates.sql", "timestamp": "2025-10-11T_s:ee:d_Z", "phase": "Phase 1: Foundation", "description": "seed interview templates"},
    {"filename": "20251027_justicehub_integration.sql", "timestamp": "2025-10-27T_j:us:tiZ", "phase": "Phase 1: Foundation", "description": "justicehub integration"},
    {"filename": "20260101000001_fix_harvested_outcomes_cascade.sql", "timestamp": "2026-01-01T00:00:01Z", "phase": "Phase 1: Foundation", "description": "fix harvested outcomes cascade"},
    {"filename": "20260101000001_phase1_remove_archive_tables.sql", "timestamp": "2026-01-01T00:00:01Z", "phase": "Phase 1: Foundation", "description": "phase1 remove archive tables"},
    {"filename": "20260101000002_audit_triggers.sql", "timestamp": "2026-01-01T00:00:02Z", "phase": "Phase 1: Foundation", "description": "audit triggers"},
    {"filename": "20260101000003_consent_revocation_cleanup.sql", "timestamp": "2026-01-01T00:00:03Z", "phase": "Phase 1: Foundation", "description": "consent revocation cleanup"},
    {"filename": "20260101000004_sync_transcript_consent.sql", "timestamp": "2026-01-01T00:00:04Z", "phase": "Phase 1: Foundation", "description": "sync transcript consent"},
    {"filename": "20260102000001_add_critical_indexes.sql", "timestamp": "2026-01-02T00:00:01Z", "phase": "Phase 1: Foundation", "description": "add critical indexes"},
    {"filename": "20260102000002_knowledge_base_schema.sql", "timestamp": "2026-01-02T00:00:02Z", "phase": "Phase 1: Foundation", "description": "knowledge base schema"},
    {"filename": "20260102000002_remove_unused_tables_phase1.sql", "timestamp": "2026-01-02T00:00:02Z", "phase": "Phase 1: Foundation", "description": "remove unused tables phase1"},
    {"filename": "20260102120000_syndication_system_schema.sql", "timestamp": "2026-01-02T12:00:00Z", "phase": "Phase 1: Foundation", "description": "syndication system schema"},
    {"filename": "20260102120000_syndication_system_schema_clean.sql", "timestamp": "2026-01-02T12:00:00Z", "phase": "Phase 1: Foundation", "description": "syndication system schema clean"},
    {"filename": "20260102120000_syndication_system_schema_fixed.sql", "timestamp": "2026-01-02T12:00:00Z", "phase": "Phase 1: Foundation", "description": "syndication system schema fixed"},
    {"filename": "20260102180000_consolidate_theme_tables.sql", "timestamp": "2026-01-02T18:00:00Z", "phase": "Phase 1: Foundation", "description": "consolidate theme tables"},
    {"filename": "20260102190000_remove_old_photo_system.sql", "timestamp": "2026-01-02T19:00:00Z", "phase": "Phase 1: Foundation", "description": "remove old photo system"},
    {"filename": "20260104000001_stories_sprint2_fields.sql", "timestamp": "2026-01-04T00:00:01Z", "phase": "Phase 1: Foundation", "description": "stories sprint2 fields"},
    {"filename": "20260104000001_story_share_tracking.sql", "timestamp": "2026-01-04T00:00:01Z", "phase": "Phase 1: Foundation", "description": "story share tracking"},
    {"filename": "20260104000002_media_assets_sprint2_fields.sql", "timestamp": "2026-01-04T00:00:02Z", "phase": "Phase 1: Foundation", "description": "media assets sprint2 fields"},
    {"filename": "20260105000000_sprint3_comments_system.sql", "timestamp": "2026-01-05T00:00:00Z", "phase": "Phase 1: Foundation", "description": "sprint3 comments system"},
    {"filename": "20260105000000_sprint5_organization_tools.sql", "timestamp": "2026-01-05T00:00:00Z", "phase": "Phase 1: Foundation", "description": "sprint5 organization tools"},
    {"filename": "20260105120000_sprint4_story_versions.sql", "timestamp": "2026-01-05T12:00:00Z", "phase": "Phase 1: Foundation", "description": "sprint4 story versions"},
    {"filename": "20260105120001_sprint4_story_collaborators.sql", "timestamp": "2026-01-05T12:00:01Z", "phase": "Phase 1: Foundation", "description": "sprint4 story collaborators"},
    {"filename": "20260105120002_sprint4_media_enhancements.sql", "timestamp": "2026-01-05T12:00:02Z", "phase": "Phase 1: Foundation", "description": "sprint4 media enhancements"},
    {"filename": "20260106000001_transcript_analysis_results.sql", "timestamp": "2026-01-06T00:00:01Z", "phase": "Phase 1: Foundation", "description": "transcript analysis results"},
    {"filename": "20260106000002_fix_audit_logs_constraint.sql", "timestamp": "2026-01-06T00:00:02Z", "phase": "Phase 1: Foundation", "description": "fix audit logs constraint"},
    {"filename": "20260106000003_create_storytellers_table.sql", "timestamp": "2026-01-06T00:00:03Z", "phase": "Phase 1: Foundation", "description": "create storytellers table"},
    {"filename": "20260106000004_consolidate_storytellers.sql", "timestamp": "2026-01-06T00:00:04Z", "phase": "Phase 1: Foundation", "description": "consolidate storytellers"},
    {"filename": "20260106120000_deprecate_old_analysis_tables.sql", "timestamp": "2026-01-06T12:00:00Z", "phase": "Phase 1: Foundation", "description": "deprecate old analysis tables"},
    {"filename": "20260107000001_fix_stories_storyteller_fk.sql", "timestamp": "2026-01-07T00:00:01Z", "phase": "Phase 2: Storyteller System", "description": "fix stories storyteller fk"},
    {"filename": "20260107000002_fix_transcripts_storyteller_fk.sql", "timestamp": "2026-01-07T00:00:02Z", "phase": "Phase 2: Storyteller System", "description": "fix transcripts storyteller fk"},
    {"filename": "20260108000001_phase3_theme_system_buildout.sql", "timestamp": "2026-01-08T00:00:01Z", "phase": "Phase 2: Storyteller System", "description": "phase3 theme system buildout"},
    {"filename": "20260108000002_add_storyteller_columns.sql", "timestamp": "2026-01-08T00:00:02Z", "phase": "Phase 2: Storyteller System", "description": "add storyteller columns"},
    {"filename": "20260108000003_fix_project_storytellers_fk.sql", "timestamp": "2026-01-08T00:00:03Z", "phase": "Phase 2: Storyteller System", "description": "fix project storytellers fk"},
    {"filename": "20260108000004_create_storyteller_system.sql", "timestamp": "2026-01-08T00:00:04Z", "phase": "Phase 2: Storyteller System", "description": "create storyteller system"},
    {"filename": "20260108000005_add_storyteller_boolean_columns.sql", "timestamp": "2026-01-08T00:00:05Z", "phase": "Phase 2: Storyteller System", "description": "add storyteller boolean columns"},
    {"filename": "20260108_video_links.sql", "timestamp": "2026-01-08T_v:id:eoZ", "phase": "Phase 2: Storyteller System", "description": "video links"},
    {"filename": "20260109000001_content_hub_schema.sql", "timestamp": "2026-01-09T00:00:01Z", "phase": "Phase 3: Theme System", "description": "content hub schema"},
    {"filename": "20260109000002_enhanced_media_tagging.sql", "timestamp": "2026-01-09T00:00:02Z", "phase": "Phase 3: Theme System", "description": "enhanced media tagging"},
    {"filename": "20260110000001_webflow_blog_migration.sql", "timestamp": "2026-01-10T00:00:01Z", "phase": "Phase 4: Content & Email", "description": "webflow blog migration"},
    {"filename": "20260110000100_merge_articles_into_stories.sql", "timestamp": "2026-01-10T00:01:00Z", "phase": "Phase 4: Content & Email", "description": "merge articles into stories"},
    {"filename": "20260110000101_add_import_tracking_to_stories.sql", "timestamp": "2026-01-10T00:01:01Z", "phase": "Phase 4: Content & Email", "description": "add import tracking to stories"},
    {"filename": "20260110000102_deprecate_articles_table.sql", "timestamp": "2026-01-10T00:01:02Z", "phase": "Phase 4: Content & Email", "description": "deprecate articles table"},
    {"filename": "20260110000103_super_admin_role.sql", "timestamp": "2026-01-10T00:01:03Z", "phase": "Phase 4: Content & Email", "description": "super admin role"},
    {"filename": "20260110000103_super_admin_role_fixed.sql", "timestamp": "2026-01-10T00:01:03Z", "phase": "Phase 4: Content & Email", "description": "super admin role fixed"},
    {"filename": "20260110000104_grant_super_admin_to_benjamin.sql", "timestamp": "2026-01-10T00:01:04Z", "phase": "Phase 4: Content & Email", "description": "grant super admin to benjamin"},
    {"filename": "20260111000001_fix_stories_schema.sql", "timestamp": "2026-01-11T00:00:01Z", "phase": "Phase 4: Content & Email", "description": "fix stories schema"},
    {"filename": "20260111000002_stories_editorial_columns.sql", "timestamp": "2026-01-11T00:00:02Z", "phase": "Phase 4: Content & Email", "description": "stories editorial columns"},
    {"filename": "20260111000003_email_notifications.sql", "timestamp": "2026-01-11T00:00:03Z", "phase": "Phase 4: Content & Email", "description": "email notifications"}
  ]
}
